[
  {
    "firstname": "evie",
    "lastname": "ford",
    "patronymic": "brennan"
  },
  {
    "firstname": "augustine",
    "lastname": "hammond"
  },
  {
    "firstname": "lorenzo",
    "lastname": "ramirez"
  },
  {
    "firstname": "andrea",
    "lastname": "olsen",
    "patronymic": "harmony"
  },
  {
    "firstname": "skyler",
    "lastname": "davila"
  },
  {
    "firstname": "zhuri",
    "lastname": "rodriguez",
    "patronymic": "terra"
  },
  {
    "firstname": "valentin",
    "lastname": "franco"
  },
  {
    "firstname": "camryn",
    "lastname": "novak"
  },
  {
    "firstname": "mohammed",
    "lastname": "kent",
    "patronymic": "amari"
  },
  {
    "firstname": "jazmine",
    "lastname": "mathews"
  },
  {
    "firstname": "ella",
    "lastname": "parker",
    "patronymic": "madison"
  },
  {
    "firstname": "karter",
    "lastname": "moses"
  }
]
